txt.py
txtint-0.1.2.dist-info/METADATA
txtint-0.1.2.dist-info/WHEEL
txtint-0.1.2.dist-info/RECORD
