Metadata-Version: 2.1
Name: txtint
Version: 0.1.2
Summary: tools for metamodern text interfaces
Home-page: https://ragt.ag/code/projects/txtint
License: BSD-2-Clause
Keywords: CLI,TUI
Author: Angelo Gladding
Author-email: angelo@ragt.ag
Requires-Python: >=3.8,<3.11
Classifier: License :: OSI Approved :: BSD License
Classifier: Programming Language :: Python :: 3
Classifier: Programming Language :: Python :: 3.8
Classifier: Programming Language :: Python :: 3.9
Classifier: Programming Language :: Python :: 3.10
Requires-Dist: argcomplete (>=2.0.0,<3.0.0)
Requires-Dist: rich (>=13.2.0,<14.0.0)
Project-URL: Documentation, https://ragt.ag/code/projects/txtint/api
Project-URL: Repository, https://ragt.ag/code/projects/txtint.git
